salesmanago_toolkit/__init__.py
salesmanago_toolkit/service/__init__.py
salesmanago_toolkit/service/sales_manago_actions.py
salesmanago_toolkit/utils/__init__.py
salesmanago_toolkit/utils/constants.py
salesmanago_toolkit/utils/logging_handler.py
salesmanago_toolkit/utils/sales_manago_utils.py
salesmanago_toolkit/utils/util_funcs.py
salesmanago_toolkit-0.2.18.dist-info/METADATA
salesmanago_toolkit-0.2.18.dist-info/WHEEL
salesmanago_toolkit-0.2.18.dist-info/top_level.txt
salesmanago_toolkit-0.2.18.dist-info/RECORD
