Metadata-Version: 2.2
Name: salesmanago-toolkit
Version: 0.2.18
Summary: Salesmanago Tools is a project designed to simplify working with the Salesmanago API
Home-page: https://github.com/Web-parsers/SalesmanagoTools
Author: Webparsers
Author-email: panenotgeor@gmail.com
Classifier: Programming Language :: Python :: 3
Classifier: License :: OSI Approved :: MIT License
Classifier: Operating System :: OS Independent
Requires-Python: >=3.7
Requires-Dist: aiohttp==3.11.11
Requires-Dist: requests==2.32.3
Requires-Dist: pandas<2.2
Requires-Dist: httpx==0.28.1
Dynamic: author
Dynamic: author-email
Dynamic: classifier
Dynamic: description
Dynamic: description-content-type
Dynamic: home-page
Dynamic: requires-dist
Dynamic: requires-python
Dynamic: summary
